ezyquant_execution/__init__.py
ezyquant_execution/_version.py
ezyquant_execution/config.py
ezyquant_execution/constant.py
ezyquant_execution/context.py
ezyquant_execution/derivative_context.py
ezyquant_execution/derivative_entity.py
ezyquant_execution/entity.py
ezyquant_execution/environment.py
ezyquant_execution/executing.py
ezyquant_execution/realtime.py
ezyquant_execution/utils.py
ezyquant_execution-0.1.3.dist-info/LICENSE.txt
ezyquant_execution-0.1.3.dist-info/METADATA
ezyquant_execution-0.1.3.dist-info/WHEEL
ezyquant_execution-0.1.3.dist-info/top_level.txt
ezyquant_execution-0.1.3.dist-info/RECORD
