Metadata-Version: 2.1
Name: ezyquant-execution
Version: 0.1.3
Summary: Ezyquant execution
Home-page: https://pydoc.ezyquant.com/
Author: Fintech (Thailand) Company Limited
Author-email: admin@fintech.co.th
Maintainer: Fintech (Thailand) Company Limited
Maintainer-email: admin@fintech.co.th
License: The MIT License (MIT)
Project-URL: Documentation, https://pydoc.ezyquant.com/
Project-URL: Bug Reports, https://github.com/ezyquant/ezyquant-execution/issues
Project-URL: Source, https://github.com/ezyquant/ezyquant-execution
Classifier: Intended Audience :: Financial and Insurance Industry
Classifier: Programming Language :: Python :: 3
Classifier: License :: OSI Approved :: MIT License
Requires-Python: >=3.8
License-File: LICENSE.txt
Requires-Dist: pandas >=1.3
Requires-Dist: settrade-v2 <2.2,>=2.1
